{
  "generated_at": "2026-06-05T21:00:31+08:00",
  "source": "launch-hunter",
  "signal_date": "2026-06-05",
  "top5": [
    {
      "rank": 1,
      "code": "3441",
      "name": "聯一光",
      "close": 60.2,
      "chg": 0.0985,
      "vr20": 2.39,
      "chg60": 0.8326,
      "pct_b": 0.927,
      "score_v2": 6.44,
      "ma60": 38.44,
      "stop_15pct": 51.17,
      "lock_30": 78.26,
      "lock_75": 105.35,
      "lock_170": 162.54,
      "gap_threshold_pct": 3.5,
      "gap_trigger_price": 62.31,
      "risk_tag": "最不過熱"
    },
    {
      "rank": 2,
      "code": "3363",
      "name": "上詮",
      "close": 908.0,
      "chg": 0.081,
      "vr20": 2.14,
      "chg60": 0.593,
      "pct_b": 0.903,
      "score_v2": 5.14,
      "ma60": 772.8,
      "stop_15pct": 771.8,
      "lock_30": 1180.4,
      "lock_75": 1589.0,
      "lock_170": 2451.6,
      "gap_threshold_pct": 5.0,
      "gap_trigger_price": 953.4,
      "risk_tag": "最不過熱"
    },
    {
      "rank": 3,
      "code": "4939",
      "name": "亞電",
      "close": 59.7,
      "chg": 0.0994,
      "vr20": 2.14,
      "chg60": 0.9013,
      "pct_b": 1.037,
      "score_v2": 3.45,
      "ma60": 38.34,
      "stop_15pct": 50.75,
      "lock_30": 77.61,
      "lock_75": 104.48,
      "lock_170": 161.19,
      "gap_threshold_pct": 2.5,
      "gap_trigger_price": 61.19,
      "risk_tag": "短期過熱"
    },
    {
      "rank": 4,
      "code": "6005",
      "name": "群益證",
      "close": 45.05,
      "chg": 0.0612,
      "vr20": 1.87,
      "chg60": 0.6234,
      "pct_b": 1.015,
      "score_v2": 2.13,
      "ma60": 30.59,
      "stop_15pct": 38.29,
      "lock_30": 58.56,
      "lock_75": 78.84,
      "lock_170": 121.64,
      "gap_threshold_pct": 3.5,
      "gap_trigger_price": 46.63,
      "risk_tag": "中性"
    },
    {
      "rank": 5,
      "code": "5864",
      "name": "致和證",
      "close": 53.6,
      "chg": 0.0593,
      "vr20": 1.67,
      "chg60": 1.2427,
      "pct_b": 1.046,
      "score_v2": 1.53,
      "ma60": 29.83,
      "stop_15pct": 45.56,
      "lock_30": 69.68,
      "lock_75": 93.8,
      "lock_170": 144.72,
      "gap_threshold_pct": 1.5,
      "gap_trigger_price": 54.4,
      "risk_tag": "短期過熱"
    }
  ]
}